science_of_science_pipeline_udt-0.1.5.dist-info/licenses/LICENSE
sos_pipeline_udt/__init__.py
sos_pipeline_udt/config.py
sos_pipeline_udt/corpus_overview.py
sos_pipeline_udt/network_metrics.py
sos_pipeline_udt/run_dashboard.py
sos_pipeline_udt/analysis/__init__.py
sos_pipeline_udt/analysis/embeddings.py
sos_pipeline_udt/analysis/metrics.py
sos_pipeline_udt/analysis/networks.py
sos_pipeline_udt/cache/__init__.py
sos_pipeline_udt/cache/raw_openalex_urban_digital_twin.json
sos_pipeline_udt/cache/raw_openalex_urban_digital_twin.jsonl
sos_pipeline_udt/cache/urban_digital_twin.json
sos_pipeline_udt/cache/urban_digital_twin.meta.json
sos_pipeline_udt/classification/__init__.py
sos_pipeline_udt/classification/keyword_classification.py
sos_pipeline_udt/classification/keyword_labels.json
sos_pipeline_udt/dashboard/__init__.py
sos_pipeline_udt/dashboard/callbacks_overall.py
sos_pipeline_udt/dashboard/callbacks_stats.py
sos_pipeline_udt/dashboard/callbacks_temporal.py
sos_pipeline_udt/dashboard/data_store.py
sos_pipeline_udt/dashboard/graph_store.py
sos_pipeline_udt/dashboard/stats_store.py
sos_pipeline_udt/dashboard/temporal_helpers.py
sos_pipeline_udt/dashboard/ui_layout.py
sos_pipeline_udt/dashboard/vis_elements.py
sos_pipeline_udt/dashboard/vis_styles.py
sos_pipeline_udt/data/__init__.py
sos_pipeline_udt/data/collectors.py
sos_pipeline_udt/data/publication.py
sos_pipeline_udt/data/publication_corpus.py
science_of_science_pipeline_udt-0.1.5.dist-info/METADATA
science_of_science_pipeline_udt-0.1.5.dist-info/WHEEL
science_of_science_pipeline_udt-0.1.5.dist-info/entry_points.txt
science_of_science_pipeline_udt-0.1.5.dist-info/top_level.txt
science_of_science_pipeline_udt-0.1.5.dist-info/RECORD
