Metadata-Version: 2.4
Name: science-of-science-pipeline-udt
Version: 0.1.5
Summary: Integrated pipeline and dashboard for tracing conceptual emergence and evolution in semantic space (UDT case study).
Author: Duco Trompert
License-Expression: MIT
Keywords: science-of-science,bibliometrics,science-mapping,networks,word2vec,openalex,dash
Classifier: Development Status :: 3 - Alpha
Classifier: Intended Audience :: Science/Research
Classifier: Programming Language :: Python :: 3
Classifier: Programming Language :: Python :: 3 :: Only
Classifier: Topic :: Scientific/Engineering :: Information Analysis
Classifier: Topic :: Scientific/Engineering :: Visualization
Requires-Python: >=3.11
License-File: LICENSE
Requires-Dist: requests>=2.31
Requires-Dist: numpy>=1.24
Requires-Dist: pandas>=2.0
Requires-Dist: networkx>=3.1
Requires-Dist: gensim>=4.3
Requires-Dist: plotly>=5.18
Requires-Dist: dash>=2.14
Requires-Dist: dash-cytoscape>=1.0.2
Provides-Extra: dev
Requires-Dist: build>=1.2.2; extra == "dev"
Requires-Dist: twine>=5.1.1; extra == "dev"
Requires-Dist: ruff>=0.5.0; extra == "dev"
Dynamic: license-file
